mcgtpy/__init__.py
mcgtpy/database.py
mcgtpy/helper_functions.py
mcgtpy/my_stats.py
mcgtpy-0.0.7.dist-info/METADATA
mcgtpy-0.0.7.dist-info/WHEEL
mcgtpy-0.0.7.dist-info/top_level.txt
mcgtpy-0.0.7.dist-info/RECORD
